LICENSE
README.md
setup.py
sc3microapi/__init__.py
sc3microapi/sc3microapi.py
sc3microapi.egg-info/PKG-INFO
sc3microapi.egg-info/SOURCES.txt
sc3microapi.egg-info/dependency_links.txt
sc3microapi.egg-info/entry_points.txt
sc3microapi.egg-info/requires.txt
sc3microapi.egg-info/top_level.txt
test/testService.py