Metadata-Version: 2.1
Name: sc3microapi
Version: 0.3.1
Summary: sc3microapi: Web service providing seamless access to information about networks/stations archived in SC3
Home-page: https://github.com/javiquinte/sc3microapi
Author: Javier Quinteros
Author-email: javier@gfz-potsdam.de
License: GPLv3
Keywords: SeisComP3 EIDA RoutingService
Platform: UNKNOWN
Classifier: Development Status :: 5 - Production/Stable
Classifier: Environment :: Web Environment
Classifier: Framework :: CherryPy
Classifier: Intended Audience :: Science/Research
Classifier: License :: OSI Approved :: GNU General Public License v3 or later (GPLv3+)
Classifier: Natural Language :: English
Classifier: Operating System :: POSIX :: Linux
Classifier: Programming Language :: Python :: 3
Classifier: Programming Language :: Python :: 3.6
Classifier: Programming Language :: Python :: 3.7
Classifier: Programming Language :: Python :: 3.8
Classifier: Programming Language :: Python :: 3.9
Classifier: Topic :: Scientific/Engineering
Classifier: Topic :: Database :: Front-Ends
Provides: sc3microapi
Requires-Python: >=3
